eth_permissions/__init__.py
eth_permissions/__main__.py
eth_permissions/abis.py
eth_permissions/access_control.py
eth_permissions/access_manager.py
eth_permissions/chaindata.py
eth_permissions/graph.py
eth_permissions/main.py
eth_permissions/utils.py
eth_permissions-0.4.0.dist-info/licenses/LICENSE.txt
eth_permissions-0.4.0.dist-info/METADATA
eth_permissions-0.4.0.dist-info/WHEEL
eth_permissions-0.4.0.dist-info/entry_points.txt
eth_permissions-0.4.0.dist-info/top_level.txt
eth_permissions-0.4.0.dist-info/RECORD
