Metadata-Version: 2.4
Name: eth-permissions
Version: 0.4.0
Summary: Library and command line tool for auditing smart contract permissions
Home-page: https://github.com/pyscaffold/pyscaffold/
Author: Ensuro
Author-email: dev@ensuro.co
License: MIT
Project-URL: Documentation, https://pyscaffold.org/
Platform: any
Classifier: Development Status :: 4 - Beta
Classifier: Programming Language :: Python
License-File: LICENSE.txt
Requires-Dist: importlib-metadata; python_version < "3.8"
Requires-Dist: eth-prototype[web3]>=1.3.1
Requires-Dist: graphviz
Provides-Extra: testing
Requires-Dist: setuptools; extra == "testing"
Requires-Dist: pytest; extra == "testing"
Requires-Dist: pytest-cov; extra == "testing"
Dynamic: license-file
